dbt/adapters/bigquery/__init__.py
dbt_bigquery_alvin-0.0.2.dist-info/METADATA
dbt_bigquery_alvin-0.0.2.dist-info/WHEEL
dbt_bigquery_alvin-0.0.2.dist-info/top_level.txt
dbt_bigquery_alvin-0.0.2.dist-info/RECORD
